LICENSE
README.md
setup.py
aggdirect_route_estimation_calculator/__init__.py
aggdirect_route_estimation_calculator.egg-info/PKG-INFO
aggdirect_route_estimation_calculator.egg-info/SOURCES.txt
aggdirect_route_estimation_calculator.egg-info/dependency_links.txt
aggdirect_route_estimation_calculator.egg-info/requires.txt
aggdirect_route_estimation_calculator.egg-info/top_level.txt